datatia/__init__.py
datatia/actions.py
datatia/datatia.py
datatia/tensor_source.py
datatia/utils.py
datatia-0.4.5.dist-info/METADATA
datatia-0.4.5.dist-info/WHEEL
datatia-0.4.5.dist-info/top_level.txt
datatia-0.4.5.dist-info/RECORD
