Metadata-Version: 2.4
Name: datatia
Version: 0.4.5
Summary: Opinionated declarative utility library for writing PyTorch dataset classes
Requires-Python: >=3.9
Requires-Dist: torch
